{"admin_feedback_schemes.md":"65a7f1e9","admin_acl_roles.md":"1db0c090","admin_acl_permissions.md":"8a85b30e","admin_acl_users.md":"9aa7aae4","admin_foods_fdbs.md":"ff293213","admin_foods_food-groups.md":"9d267f0d","admin_foods_nutrient-tables.md":"3bcc8b6f","admin_images_as-served-sets.md":"22c3214d","admin_foods_standard-units.md":"6a6399fc","admin_foods_nutrient-units.md":"d3251202","admin_acl_securables.md":"b3ebae0d","admin_foods_nutrient-types.md":"578d0616","admin_acl_index.md":"1a9b8eb4","admin_images_drinkware-sets.md":"5527bf7d","api_admin_nutrient-types.md":"00163a46","admin_images_guide-images.md":"844904fb","admin_images_image-maps.md":"6cbec5a3","admin_images_index.md":"51da5a9c","admin_index.md":"b6157197","admin_localization_languages.md":"c16821d4","admin_localization_locales.md":"b44fa766","admin_nutritionist-dictionary.md":"af524acc","admin_surveys_index.md":"c58997cb","admin_surveys_prompt-editor.md":"01265598","admin_surveys_prompt-templates.md":"4625f6f1","admin_surveys_schemes.md":"63db2c78","admin_system_job-types.md":"5f783267","admin_system_jobs.md":"0ddb783a","api_admin_authentication.md":"e94a71ae","api_admin_fdbs.md":"dc2b8e14","api_admin_images_image-maps.md":"8f53c157","api_admin_jobs.md":"4848b75b","api_admin_languages.md":"3473867e","admin_surveys_prompt-types.md":"87acbc41","admin_system_sign-in-logs.md":"e4887beb","admin_system_tasks.md":"eb5764c1","api_admin_feedback-schemes.md":"2589e71c","api_admin_images_drinkware-sets.md":"c67224f5","api_admin_food-groups.md":"aab3eabf","api_admin_user_jobs.md":"8e8d595e","api_survey_surveys-public.md":"44e090a1","api_admin_user_profile.md":"8230449e","api_admin_users.md":"efeff2ba","api_admin_locales.md":"6b18fa90","api_admin_nutrient-tables.md":"2d476ae0","config_survey_index.md":"512d0431","config_index.md":"509f849a","api_admin_surveys_submissions.md":"47809c74","config_api_session.md":"fa6428ca","api_admin_nutrient-units.md":"5287805a","api_admin_permissions.md":"8ed0f5e5","api_admin_references.md":"222cb370","api_survey_feedback.md":"4083d040","api_survey_food-data.md":"e05a982b","api_survey_food-lookup.md":"0c0a73ab","api_survey_portion-sizes.md":"c2c2252e","api_survey_surveys-respondent.md":"689d1e77","api_survey_user.md":"12cc45c9","cli_find-portion-images.md":"5205d4b1","cli_generate-env.md":"f5b1e297","cli_generate-key.md":"fa733f94","cli_generate-vapid-keys.md":"c12068d3","cli_index.md":"ca0cdd2d","config_admin_index.md":"f6314281","config_api_acl.md":"c0f2929d","config_api_application.md":"70a94f1c","config_api_cache.md":"802f0c5b","config_api_database.md":"8b2209c6","config_api_filesystem.md":"376f9185","config_api_index.md":"c33dd49d","config_api_mail.md":"1a5c2cf4","config_api_rate-limiter.md":"55bfcd34","config_api_security.md":"94b029b4","data-dictionary_index.md":"363f8b54","data-dictionary_survey.md":"1e539b79","deployment_index.md":"a5c9b533","developer_getting-started.md":"a6563204","developer_index.md":"803ae411","developer_new-prompts.md":"85d1c0e0","developer_portion-size.md":"79398bcf","developer_testing.md":"d3d49a2f","developer_vm.md":"ca0e7dd2","guides_index.md":"5ef79eac","guides_integrations.md":"ffe7ab62","config_api_log.md":"402caae6","developer_v3-survey.md":"25bba24c","overview_index.md":"034584b3","data-dictionary_admin.md":"337c4849","api_i18n.md":"7553ffb7","api_authentication.md":"c3cb8767","config_api_services.md":"1ad49ef4","index.md":"37028957","overview_database.md":"8d456975","config_api_queue.md":"b25271f0","api_admin_images_guide-images.md":"c69ceb7a","api_password.md":"5503a9ff","api_index.md":"5101eb27","api_subscriptions.md":"5579f267","api_admin_roles.md":"995e37d8","api_survey_authentication.md":"5e43a6e2","admin_acl_resources.md":"7059c515","api_admin_tasks.md":"3e9e4e3c","overview_get-started.md":"b9211f3a","api_admin_securables.md":"91d44f63","api_admin_sign-in-logs.md":"f73a332d","api_admin_signup.md":"c86dd000","api_admin_survey-scheme-questions.md":"25a98eef","api_admin_standard-units.md":"d121568d","api_admin_images_as-served-sets.md":"715ecc46","api_admin_survey-schemes.md":"ff1d6947","portal_index.md":"465c88fa","api_admin_images_as-served-images.md":"6e712082","api_admin_surveys_respondents.md":"1972e7aa","survey_index.md":"5d54976a","api_admin_surveys_surveys.md":"649594d0","overview_releases.md":"fd478bf9","overview_requirements.md":"7d68c414","overview_source-code.md":"d437182d","overview_technology-stack.md":"97c02b65","overview_versioning.md":"341441b6"}
