{"admin_images_guide-images.md":"869dd56d","admin_images_image-maps.md":"57020aeb","admin_images_index.md":"8efb82fa","admin_localization_languages.md":"8da3f95a","admin_localization_locales.md":"923b3c9c","admin_nutritionist-dictionary.md":"2a2481be","admin_index.md":"bf7eb7ab","admin_surveys_prompt-templates.md":"7021d84d","admin_surveys_prompt-types.md":"befa9d4e","admin_surveys_schemes.md":"a715743e","admin_system_job-types.md":"0db5e477","admin_surveys_prompt-editor.md":"41a4086e","admin_surveys_index.md":"7b1829b9","admin_system_tasks.md":"06e2f583","api_admin_fdbs.md":"1eabbd6d","admin_system_sign-in-logs.md":"1fe6ac13","admin_foods_fdbs.md":"57a1d718","api_admin_images_as-served-images.md":"190d00e1","admin_foods_nutrient-tables.md":"ac9a2027","admin_foods_nutrient-types.md":"08646a5b","admin_images_as-served-sets.md":"1239db39","admin_foods_nutrient-units.md":"5bc97692","admin_images_drinkware-sets.md":"b959ed21","api_admin_food-groups.md":"c336ed7c","api_admin_authentication.md":"6a9c87fd","admin_foods_standard-units.md":"783a09a5","api_admin_feedback-schemes.md":"55ab4d89","admin_acl_permissions.md":"bb676e87","admin_feedback_schemes.md":"329630af","admin_acl_resources.md":"34e8a922","admin_acl_index.md":"3690910d","admin_foods_food-groups.md":"43f343c7","admin_acl_roles.md":"d652b6f3","admin_acl_securables.md":"c6c54ef7","api_admin_images_as-served-sets.md":"2ea39dd4","admin_acl_users.md":"eb88af9d","admin_system_jobs.md":"e9eb7ffe","api_admin_images_drinkware-sets.md":"5de47b6d","cli_generate-key.md":"d5161880","api_admin_images_guide-images.md":"934eafa7","api_admin_sign-in-logs.md":"8885d353","api_admin_references.md":"493885c4","api_admin_nutrient-units.md":"f42556c9","api_admin_jobs.md":"f85af4dd","api_admin_roles.md":"5d317d6f","api_admin_images_image-maps.md":"5191f701","api_admin_securables.md":"d76db305","api_admin_locales.md":"b8f5bb5a","api_admin_nutrient-tables.md":"0e00add8","api_admin_permissions.md":"95c9541e","api_admin_signup.md":"b102273f","api_admin_surveys_respondents.md":"ee54e22b","api_admin_tasks.md":"d54784ce","api_admin_survey-schemes.md":"822eead1","api_admin_standard-units.md":"1f91cd70","api_authentication.md":"827f4406","api_admin_user_jobs.md":"66cb2545","config_api_mail.md":"30572c5d","api_admin_user_profile.md":"1bf05531","api_index.md":"c85d3068","api_password.md":"6bd90eb4","api_survey_feedback.md":"72e8d86e","api_survey_food-data.md":"172fcc76","api_survey_food-lookup.md":"5f9a67bf","api_i18n.md":"1406680b","api_survey_portion-sizes.md":"79651bf8","api_survey_user.md":"ca2c230a","api_survey_surveys-public.md":"701b67ba","data-dictionary_survey.md":"4bb98cb2","api_survey_authentication.md":"957496fb","api_survey_surveys-respondent.md":"4dd121b4","cli_generate-env.md":"41ea6e5d","cli_generate-vapid-keys.md":"7f4147ba","config_api_filesystem.md":"2474e0fb","cli_find-portion-images.md":"4285d238","config_api_acl.md":"f9da5237","config_api_cache.md":"198ecfd1","cli_index.md":"0ee91a91","config_api_index.md":"2f657e66","config_api_application.md":"ed401840","config_api_database.md":"de59efba","config_admin_index.md":"7146c998","config_api_log.md":"38da59e6","config_api_queue.md":"6ff117e6","config_api_services.md":"ee263bea","developer_portion-size.md":"b762b452","data-dictionary_index.md":"bb46816f","config_survey_index.md":"024d652e","overview_index.md":"39d6fe3a","developer_getting-started.md":"c9b86c8e","developer_index.md":"2950c937","config_api_rate-limiter.md":"19fe658d","config_api_security.md":"80a0ddd2","config_api_session.md":"796e8a4e","overview_source-code.md":"b96327ec","config_index.md":"1d392ba2","overview_technology-stack.md":"0364eae2","data-dictionary_admin.md":"2861df15","deployment_index.md":"67816357","overview_get-started.md":"e2ff7577","overview_requirements.md":"1ee3f07e","developer_v3-survey.md":"0bb8bdaf","overview_upgrade.md":"0233a7cb","index.md":"48dd5035","survey_index.md":"0d39d223","overview_releases.md":"b8d779dc","overview_versioning.md":"d3bfa3ab","api_admin_nutrient-types.md":"6d089cfc","api_admin_survey-scheme-questions.md":"b6a85ec6","api_admin_surveys_submissions.md":"87b0b1ac","api_admin_surveys_data-export.md":"36e8f61a","developer_testing.md":"e318019e","api_subscriptions.md":"3e54c0d3","developer_vm.md":"086e21f4","api_admin_languages.md":"6ef32282","api_admin_users.md":"bd602dc4","portal_index.md":"cf2dbb42","api_admin_surveys_surveys.md":"4d5a44c4"}
